Verilog/counter/counter.v
module counter (clk, rst, en, count);
   input clk, rst, en;
   output reg [4:0] count;
   always @(posedge clk) begin
      if (rst)      //复位信号
         count <= 2'b0;
      else if (en) begin //使能信号
         count <= count + 2'b1;

      // 在每个时钟上升沿打印 count 的值
         $display("count = %b", count);
      end
   end
endmodule

Verilog/counter/counter_tb.v
`timescale 1ns / 1ps
`include "counter.v"

module counter_tb;

reg clk;
reg reset;
reg enable;
wire [4:0] counter_out;

counter c1(clk,reset,enable,counter_out);



/*iverilog */
initial
begin            
  $dumpfile("wave.vcd");        //生成的vcd文件名称
  $dumpvars(0, counter_tb);     //tb模块名称
end
/*iverilog */

initial
begin
  clk=0;
  reset=1;
  enable=1;
  clk=1;
  #10
  reset=0;
end

always
  #5 clk=~clk;  

initial
  #2000 $finish;

endmodule

Verilog/counter/wave.vcd
$date
	Fri May 10 21:17:23 2024
$end
$version
	Icarus Verilog
$end
$timescale
	1ps
$end
$scope module counter_tb $end
$var wire 5 ! counter_out [4:0] $end
$var reg 1 " clk $end
$var reg 1 # enable $end
$var reg 1 $ reset $end
$scope module c1 $end
$var wire 1 " clk $end
$var wire 1 # en $end
$var wire 1 $ rst $end
$var reg 5 % count [4:0] $end
$upscope $end
$upscope $end
$enddefinitions $end
$comment Show the parameter values. $end
$dumpall
$end
#0
$dumpvars
b0 %
1$
1#
1"
b0 !
$end
#5000
0"
#10000
b1 !
b1 %
1"
0$
#15000
0"
#20000
b10 !
b10 %
1"
#25000
0"
#30000
b11 !
b11 %
1"
#35000
0"
#40000
b100 !
b100 %
1"
#45000
0"
#50000
b101 !
b101 %
1"
#55000
0"
#60000
b110 !
b110 %
1"
#65000
0"
#70000
b111 !
b111 %
1"
#75000
0"
#80000
b1000 !
b1000 %
1"
#85000
0"
#90000
b1001 !
b1001 %
1"
#95000
0"
#100000
b1010 !
b1010 %
1"
#105000
0"
#110000
b1011 !
b1011 %
1"
#115000
0"
#120000
b1100 !
b1100 %
1"
#125000
0"
#130000
b1101 !
b1101 %
1"
#135000
0"
#140000
b1110 !
b1110 %
1"
#145000
0"
#150000
b1111 !
b1111 %
1"
#155000
0"
#160000
b10000 !
b10000 %
1"
#165000
0"
#170000
b10001 !
b10001 %
1"
#175000
0"
#180000
b10010 !
b10010 %
1"
#185000
0"
#190000
b10011 !
b10011 %
1"
#195000
0"
#200000
b10100 !
b10100 %
1"
#205000
0"
#210000
b10101 !
b10101 %
1"
#215000
0"
#220000
b10110 !
b10110 %
1"
#225000
0"
#230000
b10111 !
b10111 %
1"
#235000
0"
#240000
b11000 !
b11000 %
1"
#245000
0"
#250000
b11001 !
b11001 %
1"
#255000
0"
#260000
b11010 !
b11010 %
1"
#265000
0"
#270000
b11011 !
b11011 %
1"
#275000
0"
#280000
b11100 !
b11100 %
1"
#285000
0"
#290000
b11101 !
b11101 %
1"
#295000
0"
#300000
b11110 !
b11110 %
1"
#305000
0"
#310000
b11111 !
b11111 %
1"
#315000
0"
#320000
b0 !
b0 %
1"
#325000
0"
#330000
b1 !
b1 %
1"
#335000
0"
#340000
b10 !
b10 %
1"
#345000
0"
#350000
b11 !
b11 %
1"
#355000
0"
#360000
b100 !
b100 %
1"
#365000
0"
#370000
b101 !
b101 %
1"
#375000
0"
#380000
b110 !
b110 %
1"
#385000
0"
#390000
b111 !
b111 %
1"
#395000
0"
#400000
b1000 !
b1000 %
1"
#405000
0"
#410000
b1001 !
b1001 %
1"
#415000
0"
#420000
b1010 !
b1010 %
1"
#425000
0"
#430000
b1011 !
b1011 %
1"
#435000
0"
#440000
b1100 !
b1100 %
1"
#445000
0"
#450000
b1101 !
b1101 %
1"
#455000
0"
#460000
b1110 !
b1110 %
1"
#465000
0"
#470000
b1111 !
b1111 %
1"
#475000
0"
#480000
b10000 !
b10000 %
1"
#485000
0"
#490000
b10001 !
b10001 %
1"
#495000
0"
#500000
b10010 !
b10010 %
1"
#505000
0"
#510000
b10011 !
b10011 %
1"
#515000
0"
#520000
b10100 !
b10100 %
1"
#525000
0"
#530000
b10101 !
b10101 %
1"
#535000
0"
#540000
b10110 !
b10110 %
1"
#545000
0"
#550000
b10111 !
b10111 %
1"
#555000
0"
#560000
b11000 !
b11000 %
1"
#565000
0"
#570000
b11001 !
b11001 %
1"
#575000
0"
#580000
b11010 !
b11010 %
1"
#585000
0"
#590000
b11011 !
b11011 %
1"
#595000
0"
#600000
b11100 !
b11100 %
1"
#605000
0"
#610000
b11101 !
b11101 %
1"
#615000
0"
#620000
b11110 !
b11110 %
1"
#625000
0"
#630000
b11111 !
b11111 %
1"
#635000
0"
#640000
b0 !
b0 %
1"
#645000
0"
#650000
b1 !
b1 %
1"
#655000
0"
#660000
b10 !
b10 %
1"
#665000
0"
#670000
b11 !
b11 %
1"
#675000
0"
#680000
b100 !
b100 %
1"
#685000
0"
#690000
b101 !
b101 %
1"
#695000
0"
#700000
b110 !
b110 %
1"
#705000
0"
#710000
b111 !
b111 %
1"
#715000
0"
#720000
b1000 !
b1000 %
1"
#725000
0"
#730000
b1001 !
b1001 %
1"
#735000
0"
#740000
b1010 !
b1010 %
1"
#745000
0"
#750000
b1011 !
b1011 %
1"
#755000
0"
#760000
b1100 !
b1100 %
1"
#765000
0"
#770000
b1101 !
b1101 %
1"
#775000
0"
#780000
b1110 !
b1110 %
1"
#785000
0"
#790000
b1111 !
b1111 %
1"
#795000
0"
#800000
b10000 !
b10000 %
1"
#805000
0"
#810000
b10001 !
b10001 %
1"
#815000
0"
#820000
b10010 !
b10010 %
1"
#825000
0"
#830000
b10011 !
b10011 %
1"
#835000
0"
#840000
b10100 !
b10100 %
1"
#845000
0"
#850000
b10101 !
b10101 %
1"
#855000
0"
#860000
b10110 !
b10110 %
1"
#865000
0"
#870000
b10111 !
b10111 %
1"
#875000
0"
#880000
b11000 !
b11000 %
1"
#885000
0"
#890000
b11001 !
b11001 %
1"
#895000
0"
#900000
b11010 !
b11010 %
1"
#905000
0"
#910000
b11011 !
b11011 %
1"
#915000
0"
#920000
b11100 !
b11100 %
1"
#925000
0"
#930000
b11101 !
b11101 %
1"
#935000
0"
#940000
b11110 !
b11110 %
1"
#945000
0"
#950000
b11111 !
b11111 %
1"
#955000
0"
#960000
b0 !
b0 %
1"
#965000
0"
#970000
b1 !
b1 %
1"
#975000
0"
#980000
b10 !
b10 %
1"
#985000
0"
#990000
b11 !
b11 %
1"
#995000
0"
#1000000
b100 !
b100 %
1"
#1005000
0"
#1010000
b101 !
b101 %
1"
#1015000
0"
#1020000
b110 !
b110 %
1"
#1025000
0"
#1030000
b111 !
b111 %
1"
#1035000
0"
#1040000
b1000 !
b1000 %
1"
#1045000
0"
#1050000
b1001 !
b1001 %
1"
#1055000
0"
#1060000
b1010 !
b1010 %
1"
#1065000
0"
#1070000
b1011 !
b1011 %
1"
#1075000
0"
#1080000
b1100 !
b1100 %
1"
#1085000
0"
#1090000
b1101 !
b1101 %
1"
#1095000
0"
#1100000
b1110 !
b1110 %
1"
#1105000
0"
#1110000
b1111 !
b1111 %
1"
#1115000
0"
#1120000
b10000 !
b10000 %
1"
#1125000
0"
#1130000
b10001 !
b10001 %
1"
#1135000
0"
#1140000
b10010 !
b10010 %
1"
#1145000
0"
#1150000
b10011 !
b10011 %
1"
#1155000
0"
#1160000
b10100 !
b10100 %
1"
#1165000
0"
#1170000
b10101 !
b10101 %
1"
#1175000
0"
#1180000
b10110 !
b10110 %
1"
#1185000
0"
#1190000
b10111 !
b10111 %
1"
#1195000
0"
#1200000
b11000 !
b11000 %
1"
#1205000
0"
#1210000
b11001 !
b11001 %
1"
#1215000
0"
#1220000
b11010 !
b11010 %
1"
#1225000
0"
#1230000
b11011 !
b11011 %
1"
#1235000
0"
#1240000
b11100 !
b11100 %
1"
#1245000
0"
#1250000
b11101 !
b11101 %
1"
#1255000
0"
#1260000
b11110 !
b11110 %
1"
#1265000
0"
#1270000
b11111 !
b11111 %
1"
#1275000
0"
#1280000
b0 !
b0 %
1"
#1285000
0"
#1290000
b1 !
b1 %
1"
#1295000
0"
#1300000
b10 !
b10 %
1"
#1305000
0"
#1310000
b11 !
b11 %
1"
#1315000
0"
#1320000
b100 !
b100 %
1"
#1325000
0"
#1330000
b101 !
b101 %
1"
#1335000
0"
#1340000
b110 !
b110 %
1"
#1345000
0"
#1350000
b111 !
b111 %
1"
#1355000
0"
#1360000
b1000 !
b1000 %
1"
#1365000
0"
#1370000
b1001 !
b1001 %
1"
#1375000
0"
#1380000
b1010 !
b1010 %
1"
#1385000
0"
#1390000
b1011 !
b1011 %
1"
#1395000
0"
#1400000
b1100 !
b1100 %
1"
#1405000
0"
#1410000
b1101 !
b1101 %
1"
#1415000
0"
#1420000
b1110 !
b1110 %
1"
#1425000
0"
#1430000
b1111 !
b1111 %
1"
#1435000
0"
#1440000
b10000 !
b10000 %
1"
#1445000
0"
#1450000
b10001 !
b10001 %
1"
#1455000
0"
#1460000
b10010 !
b10010 %
1"
#1465000
0"
#1470000
b10011 !
b10011 %
1"
#1475000
0"
#1480000
b10100 !
b10100 %
1"
#1485000
0"
#1490000
b10101 !
b10101 %
1"
#1495000
0"
#1500000
b10110 !
b10110 %
1"
#1505000
0"
#1510000
b10111 !
b10111 %
1"
#1515000
0"
#1520000
b11000 !
b11000 %
1"
#1525000
0"
#1530000
b11001 !
b11001 %
1"
#1535000
0"
#1540000
b11010 !
b11010 %
1"
#1545000
0"
#1550000
b11011 !
b11011 %
1"
#1555000
0"
#1560000
b11100 !
b11100 %
1"
#1565000
0"
#1570000
b11101 !
b11101 %
1"
#1575000
0"
#1580000
b11110 !
b11110 %
1"
#1585000
0"
#1590000
b11111 !
b11111 %
1"
#1595000
0"
#1600000
b0 !
b0 %
1"
#1605000
0"
#1610000
b1 !
b1 %
1"
#1615000
0"
#1620000
b10 !
b10 %
1"
#1625000
0"
#1630000
b11 !
b11 %
1"
#1635000
0"
#1640000
b100 !
b100 %
1"
#1645000
0"
#1650000
b101 !
b101 %
1"
#1655000
0"
#1660000
b110 !
b110 %
1"
#1665000
0"
#1670000
b111 !
b111 %
1"
#1675000
0"
#1680000
b1000 !
b1000 %
1"
#1685000
0"
#1690000
b1001 !
b1001 %
1"
#1695000
0"
#1700000
b1010 !
b1010 %
1"
#1705000
0"
#1710000
b1011 !
b1011 %
1"
#1715000
0"
#1720000
b1100 !
b1100 %
1"
#1725000
0"
#1730000
b1101 !
b1101 %
1"
#1735000
0"
#1740000
b1110 !
b1110 %
1"
#1745000
0"
#1750000
b1111 !
b1111 %
1"
#1755000
0"
#1760000
b10000 !
b10000 %
1"
#1765000
0"
#1770000
b10001 !
b10001 %
1"
#1775000
0"
#1780000
b10010 !
b10010 %
1"
#1785000
0"
#1790000
b10011 !
b10011 %
1"
#1795000
0"
#1800000
b10100 !
b10100 %
1"
#1805000
0"
#1810000
b10101 !
b10101 %
1"
#1815000
0"
#1820000
b10110 !
b10110 %
1"
#1825000
0"
#1830000
b10111 !
b10111 %
1"
#1835000
0"
#1840000
b11000 !
b11000 %
1"
#1845000
0"
#1850000
b11001 !
b11001 %
1"
#1855000
0"
#1860000
b11010 !
b11010 %
1"
#1865000
0"
#1870000
b11011 !
b11011 %
1"
#1875000
0"
#1880000
b11100 !
b11100 %
1"
#1885000
0"
#1890000
b11101 !
b11101 %
1"
#1895000
0"
#1900000
b11110 !
b11110 %
1"
#1905000
0"
#1910000
b11111 !
b11111 %
1"
#1915000
0"
#1920000
b0 !
b0 %
1"
#1925000
0"
#1930000
b1 !
b1 %
1"
#1935000
0"
#1940000
b10 !
b10 %
1"
#1945000
0"
#1950000
b11 !
b11 %
1"
#1955000
0"
#1960000
b100 !
b100 %
1"
#1965000
0"
#1970000
b101 !
b101 %
1"
#1975000
0"
#1980000
b110 !
b110 %
1"
#1985000
0"
#1990000
b111 !
b111 %
1"
#1995000
0"
#2000000
b1000 !
b1000 %
1"
